README.rst
setup.py
slowjam/__init__.py
slowjam/context.py
slowjam/proxy.py
slowjam/statsd_client.py
slowjam/trace.py
slowjam.egg-info/PKG-INFO
slowjam.egg-info/SOURCES.txt
slowjam.egg-info/dependency_links.txt
slowjam.egg-info/not-zip-safe
slowjam.egg-info/pbr.json
slowjam.egg-info/top_level.txt
slowjam/ext/__init__.py
slowjam/ext/django/__init__.py
slowjam/ext/django/middleware.py