Metadata-Version: 1.1
Name: slowjam
Version: 1.3.3
Summary: Python Application Tracer
Home-page: https://github.com/voidfiles/slowjam
Author: Bryan Berg, Mark Thurman, Alex Kessinger
Author-email: UNKNOWN
License: MIT
Platform: UNKNOWN
Classifier: Development Status :: 5 - Production/Stable
